sparseutils/mksparse.py
sparseutils/sparsemap.py
sparseutils-0.1.0.dist-info/COPYING
sparseutils-0.1.0.dist-info/METADATA
sparseutils-0.1.0.dist-info/WHEEL
sparseutils-0.1.0.dist-info/entry_points.txt
sparseutils-0.1.0.dist-info/top_level.txt
sparseutils-0.1.0.dist-info/RECORD
