Metadata-Version: 2.1
Name: sparseutils
Version: 0.1.0
Summary: Utilities for interacting with sparse files
Author: Richard Ipsum
Author-email: richardipsum@vx21.xyz
License: UNKNOWN
Keywords: sparse
Platform: UNKNOWN
Classifier: Development Status :: 5 - Production/Stable
Classifier: Environment :: Console
Classifier: Intended Audience :: Developers
Classifier: License :: OSI Approved :: GNU General Public License v3 or later (GPLv3+)
Classifier: Operating System :: POSIX :: Linux
Classifier: Programming Language :: Python :: 3
Classifier: Topic :: Utilities
License-File: COPYING
